govee_mcp_server/__init__.py
govee_mcp_server/api.py
govee_mcp_server/cli.py
govee_mcp_server/config.py
govee_mcp_server/exceptions.py
govee_mcp_server/interfaces.py
govee_mcp_server/server.py
govee_mcp_server/transformers.py
mseep_govee_mcp_server-0.1.4.dist-info/METADATA
mseep_govee_mcp_server-0.1.4.dist-info/WHEEL
mseep_govee_mcp_server-0.1.4.dist-info/entry_points.txt
mseep_govee_mcp_server-0.1.4.dist-info/licenses/LICENSE
mseep_govee_mcp_server-0.1.4.dist-info/RECORD
