Metadata-Version: 2.4
Name: mseep-govee-mcp-server
Version: 0.1.4
Summary: MCP server to control Govee LED devices
Author-email: mseep <support@skydeck.ai>
License-File: LICENSE
Requires-Python: >=3.10
Requires-Dist: govee-api-laggat>=0.2.2
Requires-Dist: mcp[cli]
Requires-Dist: python-dotenv
Provides-Extra: test
Requires-Dist: pytest-asyncio>=0.21.0; extra == 'test'
Requires-Dist: pytest-mock>=3.10.0; extra == 'test'
Requires-Dist: pytest>=7.0; extra == 'test'
